sendlayer/VERSION
sendlayer/__init__.py
sendlayer/exceptions.py
sendlayer/version.py
sendlayer/base/__init__.py
sendlayer/base/base.py
sendlayer/email/__init__.py
sendlayer/email/email.py
sendlayer/events/__init__.py
sendlayer/events/events.py
sendlayer/webhooks/__init__.py
sendlayer/webhooks/webhooks.py
sendlayer-1.0.0.dist-info/licenses/LICENSE
sendlayer-1.0.0.dist-info/METADATA
sendlayer-1.0.0.dist-info/WHEEL
sendlayer-1.0.0.dist-info/top_level.txt
sendlayer-1.0.0.dist-info/RECORD
