Metadata-Version: 2.4
Name: sendlayer
Version: 1.0.0
Summary: Official Python SDK for SendLayer API
Home-page: https://github.com/sendlayer/sendlayer-python
Author: SendLayer
Author-email: SendLayer <support@sendlayer.com>
Maintainer: David Ozokoye
Project-URL: Homepage, https://github.com/sendlayer/sendlayer-python
Keywords: email,sendlayer,sdk,api,transactional email,mail,send email,email api,sendlayer api,send email python,python email package
Classifier: Development Status :: 4 - Beta
Classifier: Intended Audience :: Developers
Classifier: License :: OSI Approved :: MIT License
Classifier: Operating System :: OS Independent
Classifier: Programming Language :: Python :: 3
Classifier: Programming Language :: Python :: 3.7
Classifier: Programming Language :: Python :: 3.8
Classifier: Programming Language :: Python :: 3.9
Classifier: Programming Language :: Python :: 3.10
Classifier: Programming Language :: Python :: 3.11
Requires-Python: >=3.7
License-File: LICENSE
Requires-Dist: requests>=2.25.0
Dynamic: author
Dynamic: home-page
Dynamic: license-file
Dynamic: requires-python
